{
  "collapse-filter": false,
  "search": "",
  "showTags": false,
  "showAttachments": false,
  "hideUnresolved": false,
  "showOrphans": true,
  "collapse-color-groups": false,
  "colorGroups": [
    {
      "query": "tag:#timber-hearth",
      "color": {
        "a": 1,
        "rgb": 11657298
      }
    },
    {
      "query": "tag:#ash-twin",
      "color": {
        "a": 1,
        "rgb": 14113627
      }
    },
    {
      "query": "tag:#ember-twin",
      "color": {
        "a": 1,
        "rgb": 12066334
      }
    },
    {
      "query": "tag:#brittle-hollow",
      "color": {
        "a": 1,
        "rgb": 5419488
      }
    },
    {
      "query": "tag:#dark-bramble",
      "color": {
        "a": 1,
        "rgb": 798825
      }
    },
    {
      "query": "tag:#quantum-moon",
      "color": {
        "a": 1,
        "rgb": 4423606
      }
    },
    {
      "query": "tag:#giants-deep",
      "color": {
        "a": 1,
        "rgb": 2935181
      }
    },
    {
      "query": "tag:#eye-of-the-universe",
      "color": {
        "a": 1,
        "rgb": 5590471
      }
    },
    {
      "query": "tag:#sun",
      "color": {
        "a": 1,
        "rgb": 14964492
      }
    },
    {
      "query": "tag:#mechanics",
      "color": {
        "a": 1,
        "rgb": 5419488
      }
    },
    {
      "query": "tag:#outer-wilds",
      "color": {
        "a": 1,
        "rgb": 16242434
      }
    }
  ],
  "collapse-display": false,
  "showArrow": false,
  "textFadeMultiplier": -1.7,
  "nodeSizeMultiplier": 1.7078125,
  "lineSizeMultiplier": 1.478125,
  "collapse-forces": false,
  "centerStrength": 0.348958333333333,
  "repelStrength": 9.79166666666667,
  "linkStrength": 0.739583333333333,
  "linkDistance": 302,
  "scale": 0.2588386562181703,
  "close": false
}